sceptre_cloudfront_invalidation_hook.py
sceptre_cloudfront_invalidation_hook-0.1.dist-info/LICENSE
sceptre_cloudfront_invalidation_hook-0.1.dist-info/METADATA
sceptre_cloudfront_invalidation_hook-0.1.dist-info/WHEEL
sceptre_cloudfront_invalidation_hook-0.1.dist-info/entry_points.txt
sceptre_cloudfront_invalidation_hook-0.1.dist-info/top_level.txt
sceptre_cloudfront_invalidation_hook-0.1.dist-info/RECORD
