Metadata-Version: 2.1
Name: sceptre-cloudfront-invalidation-hook
Version: 0.1
Summary: A hook for triggering CloudFront invalidation.
Home-page: https://github.com/trinopoty/sceptre-cloudfront-invalidation-hook
Author: Trinopoty Biswas
Author-email: Trinopoty Biswas <trinopoty@outlook.com>
Project-URL: Homepage, https://github.com/trinopoty/sceptre-cloudfront-invalidation-hook
Project-URL: Issues, https://github.com/trinopoty/sceptre-cloudfront-invalidation-hook/issues
Classifier: Programming Language :: Python :: 3
Classifier: License :: OSI Approved :: MIT License
Classifier: Operating System :: OS Independent
Requires-Python: >=3.10
License-File: LICENSE
